LICENSE.txt
MANIFEST.in
README.rst
setup.cfg
setup.py
pyhydrotel/__init__.py
pyhydrotel/core.py
pyhydrotel.egg-info/PKG-INFO
pyhydrotel.egg-info/SOURCES.txt
pyhydrotel.egg-info/dependency_links.txt
pyhydrotel.egg-info/requires.txt
pyhydrotel.egg-info/top_level.txt
pyhydrotel/tests/__init__.py
pyhydrotel/tests/get_Hydrotel.py
pyhydrotel/tests/test_hydrotel.py