Metadata-Version: 1.1
Name: pyhydrotel
Version: 1.1.4
Summary: Functions to extract data from hydrotel
Home-page: https://github.com/mullenkamp/pyhydrotel
Author: Mike Kittridge
Author-email: mullenkamp1@gmail.com
License: UNKNOWN
Keywords: hydrotel
Platform: UNKNOWN
Classifier: Development Status :: 3 - Alpha
Classifier: Intended Audience :: Developers
Classifier: Topic :: Software Development :: Build Tools
Classifier: License :: OSI Approved :: Apache Software License
Classifier: Programming Language :: Python :: 2
Classifier: Programming Language :: Python :: 2.7
Classifier: Programming Language :: Python :: 3
Classifier: Programming Language :: Python :: 3.4
Classifier: Programming Language :: Python :: 3.5
Classifier: Programming Language :: Python :: 3.6
